http_hoba_auth/__init__.py
http_hoba_auth/hoba.py
http_hoba_auth-0.2.0.dist-info/LICENSE.txt
http_hoba_auth-0.2.0.dist-info/METADATA
http_hoba_auth-0.2.0.dist-info/WHEEL
http_hoba_auth-0.2.0.dist-info/top_level.txt
http_hoba_auth-0.2.0.dist-info/RECORD
