Metadata-Version: 2.1
Name: http-hoba-auth
Version: 0.2.0
Summary: Python implementation of the HTTP Origin-Bound Auth (HOBA) scheme
Home-page: https://gitlab.com/nolash/python-http-hoba-auth
Author: Louis Holbrook
Author-email: dev@holbrook.no
License: GPL3
Keywords: http,internet,authentication,cryptography
Platform: UNKNOWN
Classifier: Programming Language :: Python :: 3
Classifier: Operating System :: OS Independent
Classifier: Development Status :: 3 - Alpha
Classifier: Intended Audience :: Developers
Classifier: License :: OSI Approved :: GNU General Public License v3 or later (GPLv3+)
Classifier: Topic :: Software Development :: Libraries
Classifier: Topic :: Internet
Requires-Python: >=3.6
